[
  {
    "solver": "Vala",
    "runType": "automated",
    "timestamp": "2026-01-18T12:02:28Z",
    "results": [
      {
        "matrix": "1",
        "time": 6.4305,
        "iterations": 0,
        "memory": 1835008,
        "cpu_user": 1.831,
        "cpu_sys": 2.914,
        "page_faults_major": 5,
        "page_faults_minor": 705,
        "context_switches_voluntary": 1,
        "context_switches_involuntary": 18,
        "io_inputs": 0,
        "io_outputs": 0,
        "status": "error",
        "output": "\n"
      },
      {
        "matrix": "2",
        "time": 6.1802,
        "iterations": 0,
        "memory": 1835008,
        "cpu_user": 1.833,
        "cpu_sys": 2.785,
        "page_faults_major": 5,
        "page_faults_minor": 705,
        "context_switches_voluntary": 1,
        "context_switches_involuntary": 15,
        "io_inputs": 0,
        "io_outputs": 0,
        "status": "error",
        "output": "\n"
      },
      {
        "matrix": "3",
        "time": 6.4569,
        "iterations": 0,
        "memory": 1835008,
        "cpu_user": 1.835,
        "cpu_sys": 2.669,
        "page_faults_major": 5,
        "page_faults_minor": 708,
        "context_switches_voluntary": 1,
        "context_switches_involuntary": 16,
        "io_inputs": 0,
        "io_outputs": 0,
        "status": "error",
        "output": "\n"
      },
      {
        "matrix": "4",
        "time": 6.2008,
        "iterations": 0,
        "memory": 1835008,
        "cpu_user": 1.833,
        "cpu_sys": 2.661,
        "page_faults_major": 5,
        "page_faults_minor": 707,
        "context_switches_voluntary": 1,
        "context_switches_involuntary": 11,
        "io_inputs": 0,
        "io_outputs": 0,
        "status": "error",
        "output": "\n"
      },
      {
        "matrix": "5",
        "time": 6.1908,
        "iterations": 0,
        "memory": 1835008,
        "cpu_user": 1.851,
        "cpu_sys": 2.678,
        "page_faults_major": 5,
        "page_faults_minor": 706,
        "context_switches_voluntary": 1,
        "context_switches_involuntary": 12,
        "io_inputs": 0,
        "io_outputs": 0,
        "status": "error",
        "output": "\n"
      },
      {
        "matrix": "6",
        "time": 6.7971,
        "iterations": 0,
        "memory": 1835008,
        "cpu_user": 2.021,
        "cpu_sys": 2.895,
        "page_faults_major": 5,
        "page_faults_minor": 707,
        "context_switches_voluntary": 1,
        "context_switches_involuntary": 14,
        "io_inputs": 0,
        "io_outputs": 0,
        "status": "error",
        "output": "\n"
      }
    ]
  }
]
