[
  {
    "solver": "OCaml",
    "runType": "automated",
    "timestamp": "2026-01-18T12:02:20Z",
    "results": [
      {
        "matrix": "1",
        "time": 6.1495,
        "iterations": 0,
        "memory": 1835008,
        "cpu_user": 1.68,
        "cpu_sys": 2.66,
        "page_faults_major": 5,
        "page_faults_minor": 709,
        "context_switches_voluntary": 1,
        "context_switches_involuntary": 17,
        "io_inputs": 0,
        "io_outputs": 0,
        "status": "error",
        "output": "\n"
      },
      {
        "matrix": "2",
        "time": 6.1987,
        "iterations": 0,
        "memory": 1835008,
        "cpu_user": 1.708,
        "cpu_sys": 2.677,
        "page_faults_major": 5,
        "page_faults_minor": 707,
        "context_switches_voluntary": 1,
        "context_switches_involuntary": 15,
        "io_inputs": 0,
        "io_outputs": 0,
        "status": "error",
        "output": "\n"
      },
      {
        "matrix": "3",
        "time": 6.2408,
        "iterations": 0,
        "memory": 1835008,
        "cpu_user": 1.777,
        "cpu_sys": 2.686,
        "page_faults_major": 5,
        "page_faults_minor": 708,
        "context_switches_voluntary": 1,
        "context_switches_involuntary": 14,
        "io_inputs": 0,
        "io_outputs": 0,
        "status": "error",
        "output": "\n"
      },
      {
        "matrix": "4",
        "time": 6.5474,
        "iterations": 0,
        "memory": 1835008,
        "cpu_user": 1.816,
        "cpu_sys": 2.729,
        "page_faults_major": 5,
        "page_faults_minor": 707,
        "context_switches_voluntary": 1,
        "context_switches_involuntary": 17,
        "io_inputs": 0,
        "io_outputs": 0,
        "status": "error",
        "output": "\n"
      },
      {
        "matrix": "5",
        "time": 6.2719,
        "iterations": 0,
        "memory": 1835008,
        "cpu_user": 1.835,
        "cpu_sys": 2.648,
        "page_faults_major": 5,
        "page_faults_minor": 708,
        "context_switches_voluntary": 1,
        "context_switches_involuntary": 15,
        "io_inputs": 0,
        "io_outputs": 0,
        "status": "error",
        "output": "\n"
      },
      {
        "matrix": "6",
        "time": 6.0745,
        "iterations": 0,
        "memory": 1835008,
        "cpu_user": 1.796,
        "cpu_sys": 2.633,
        "page_faults_major": 5,
        "page_faults_minor": 706,
        "context_switches_voluntary": 1,
        "context_switches_involuntary": 10,
        "io_inputs": 0,
        "io_outputs": 0,
        "status": "error",
        "output": "\n"
      }
    ]
  }
]
